odoo10_addon_crm_phonecall_timesheet-10.0.1.0.0-py2.7-nspkg.pth
odoo/addons/crm_phonecall_timesheet/README.rst
odoo/addons/crm_phonecall_timesheet/__init__.py
odoo/addons/crm_phonecall_timesheet/__manifest__.py
odoo/addons/crm_phonecall_timesheet/i18n/es.po
odoo/addons/crm_phonecall_timesheet/models/__init__.py
odoo/addons/crm_phonecall_timesheet/models/account_analytic_line.py
odoo/addons/crm_phonecall_timesheet/models/crm_phonecall.py
odoo/addons/crm_phonecall_timesheet/static/description/icon.png
odoo/addons/crm_phonecall_timesheet/tests/__init__.py
odoo/addons/crm_phonecall_timesheet/tests/test_crm_phonecall.py
odoo/addons/crm_phonecall_timesheet/views/crm_phonecall_view.xml
odoo/addons/crm_phonecall_timesheet/views/hr_timesheet_view.xml
odoo10_addon_crm_phonecall_timesheet-10.0.1.0.0.dist-info/DESCRIPTION.rst
odoo10_addon_crm_phonecall_timesheet-10.0.1.0.0.dist-info/METADATA
odoo10_addon_crm_phonecall_timesheet-10.0.1.0.0.dist-info/RECORD
odoo10_addon_crm_phonecall_timesheet-10.0.1.0.0.dist-info/WHEEL
odoo10_addon_crm_phonecall_timesheet-10.0.1.0.0.dist-info/metadata.json
odoo10_addon_crm_phonecall_timesheet-10.0.1.0.0.dist-info/namespace_packages.txt
odoo10_addon_crm_phonecall_timesheet-10.0.1.0.0.dist-info/top_level.txt
